p4x/__init__.py
p4x/_version.py
p4x/case_changer.py
p4x/colorschemes.py
p4x/timing.py
p4x/git/__init__.py
p4x/laboratory/__init__.py
p4x/laboratory/experiments/__init__.py
p4x/laboratory/experiments/base.py
p4x/laboratory/experiments/exception.py
p4x/laboratory/experiments/manager.py
p4x/laboratory/experiments/project.py
p4x/laboratory/experiments/session.py
p4x/laboratory/experiments/trial.py
p4x/laboratory/experiments/marshmallow/__init__.py
p4x/laboratory/experiments/marshmallow/base.py
p4x/laboratory/experiments/marshmallow/project.py
p4x/laboratory/experiments/marshmallow/session.py
p4x/laboratory/experiments/marshmallow/trial.py
p4x-0.3.0.dist-info/AUTHORS.rst
p4x-0.3.0.dist-info/LICENSE
p4x-0.3.0.dist-info/METADATA
p4x-0.3.0.dist-info/WHEEL
p4x-0.3.0.dist-info/top_level.txt
p4x-0.3.0.dist-info/RECORD
