Metadata-Version: 2.1
Name: p4x
Version: 0.3.0
Summary: Philipp Tempel's Personal Python Package. Includes lots of self-made modules and methods.
Home-page: https://github.com/philipptempel/python-p4x
Author: Philipp Tempel
Author-email: mail@philipptempel.me
License: MIT
Project-URL: Documentation, https://python-p4x.readthedocs.io/
Project-URL: Changelog, https://python-p4x.readthedocs.io/en/latest/changelog.html
Project-URL: Issue Tracker, https://github.com/philipptempel/python-p4x/issues
Platform: UNKNOWN
Classifier: Development Status :: 5 - Production/Stable
Classifier: Intended Audience :: Developers
Classifier: License :: OSI Approved :: MIT License
Classifier: Operating System :: Unix
Classifier: Operating System :: POSIX
Classifier: Operating System :: Microsoft :: Windows
Classifier: Programming Language :: Python
Classifier: Programming Language :: Python :: 3.6
Classifier: Programming Language :: Python :: 3.7
Classifier: Programming Language :: Python :: 3.8
Classifier: Programming Language :: Python :: Implementation :: PyPy
Classifier: Topic :: Utilities
Requires-Python: >=3.6
Requires-Dist: numpy
Requires-Dist: scipy
Requires-Dist: prettyprinter
Requires-Dist: colour
Requires-Dist: matplotlib
Requires-Dist: plotly
Requires-Dist: marshmallow
Requires-Dist: gitpython
